{
  "_meta": {
    "project": "Versa Olympiads",
    "module_id": "courier",
    "generated_at": "2026-06-21T00:00:00+04:00",
    "source": {
      "master_csv": "source/versa_olympiads_master_brd_00_20.csv",
      "courier_module_source_trace": "source/courier_module_source_trace.csv",
      "source_row_count_used_for_trace": 221,
      "depends_on_completed_modules": [
        "schools",
        "students",
        "payments",
        "exam_slots",
        "exam_materials"
      ]
    },
    "generator_note": "This is a semantic compiled module spec, not a CSV-row wrapper."
  },
  "module_id": "courier",
  "collections": [
    {
      "collection": "courier_batches",
      "description": "School-level courier/dispatch/return batch for exam and answer-sheet material movement.",
      "owner": "operations",
      "primary_key": "id",
      "display_template": "{{courier_code}} - {{school_id.school_code}} - {{status}}",
      "unique_business_keys": [
        "courier_code",
        "school_id + participation_id + courier_direction + courier_version"
      ],
      "status_field": "status",
      "fields": [
        {
          "name": "id",
          "type": "uuid",
          "required": true,
          "system": true
        },
        {
          "name": "courier_code",
          "type": "string",
          "required": true,
          "unique": true,
          "pattern": "COU-[0-9]{8}"
        },
        {
          "name": "school_id",
          "type": "many-to-one:schools",
          "required": true,
          "sensitive": true
        },
        {
          "name": "participation_id",
          "type": "many-to-one:participations",
          "required": true,
          "sensitive": true
        },
        {
          "name": "exam_material_id",
          "type": "many-to-one:exam_materials",
          "required": false,
          "sensitive": true
        },
        {
          "name": "exam_slot_booking_id",
          "type": "many-to-one:exam_slot_bookings",
          "required": false,
          "sensitive": true
        },
        {
          "name": "courier_direction",
          "type": "enum",
          "required": true,
          "allowed_values": [
            "outbound_to_school",
            "return_from_school",
            "internal_to_evaluation_center"
          ]
        },
        {
          "name": "courier_provider",
          "type": "string",
          "required": false,
          "sensitive": true
        },
        {
          "name": "awb_number",
          "type": "string",
          "required": false,
          "sensitive": true
        },
        {
          "name": "tracking_url",
          "type": "string",
          "required": false,
          "sensitive": true
        },
        {
          "name": "dispatch_date",
          "type": "date",
          "required": false
        },
        {
          "name": "expected_delivery_date",
          "type": "date",
          "required": false
        },
        {
          "name": "delivered_at",
          "type": "datetime",
          "required": false
        },
        {
          "name": "received_at",
          "type": "datetime",
          "required": false
        },
        {
          "name": "expected_answer_sheet_count",
          "type": "integer",
          "required": true,
          "min": 0
        },
        {
          "name": "received_answer_sheet_count",
          "type": "integer",
          "required": false,
          "min": 0
        },
        {
          "name": "shortage_count",
          "type": "integer",
          "required": false,
          "min": 0
        },
        {
          "name": "excess_count",
          "type": "integer",
          "required": false,
          "min": 0
        },
        {
          "name": "dispatch_proof_file",
          "type": "file",
          "required": false,
          "private": true,
          "sensitive": true
        },
        {
          "name": "courier_receipt_file",
          "type": "file",
          "required": false,
          "private": true,
          "sensitive": true
        },
        {
          "name": "school_submission_declaration_file",
          "type": "file",
          "required": false,
          "private": true,
          "sensitive": true
        },
        {
          "name": "receipt_exception_notes",
          "type": "text",
          "required": false,
          "sensitive": true
        },
        {
          "name": "status",
          "type": "enum",
          "required": true,
          "default": "draft",
          "allowed_values": [
            "draft",
            "ready_for_dispatch",
            "dispatched",
            "in_transit",
            "delivered",
            "return_expected",
            "received",
            "count_mismatch",
            "exception",
            "closed",
            "cancelled",
            "archived"
          ]
        },
        {
          "name": "created_by",
          "type": "many-to-one:directus_users",
          "required": true,
          "sensitive": true
        },
        {
          "name": "received_by",
          "type": "many-to-one:directus_users",
          "required": false,
          "sensitive": true
        },
        {
          "name": "created_at",
          "type": "datetime",
          "required": true,
          "system": true
        },
        {
          "name": "updated_at",
          "type": "datetime",
          "required": true,
          "system": true
        }
      ],
      "relationships": [
        {
          "type": "many-to-one",
          "target": "schools",
          "field": "school_id"
        },
        {
          "type": "many-to-one",
          "target": "participations",
          "field": "participation_id"
        },
        {
          "type": "many-to-one",
          "target": "exam_materials",
          "field": "exam_material_id"
        },
        {
          "type": "one-to-many",
          "target": "courier_events",
          "foreign_key": "courier_batch_id"
        }
      ]
    },
    {
      "collection": "courier_events",
      "description": "Append-only courier tracking, receipt and reconciliation event ledger.",
      "owner": "operations",
      "primary_key": "id",
      "append_only": true,
      "fields": [
        {
          "name": "id",
          "type": "uuid",
          "required": true,
          "system": true
        },
        {
          "name": "courier_batch_id",
          "type": "many-to-one:courier_batches",
          "required": true,
          "sensitive": true
        },
        {
          "name": "event_code",
          "type": "string",
          "required": true
        },
        {
          "name": "event_source",
          "type": "enum",
          "required": true,
          "allowed_values": [
            "school_coordinator",
            "operations_staff",
            "system",
            "courier_provider",
            "evaluation_center"
          ]
        },
        {
          "name": "previous_status",
          "type": "string",
          "required": false
        },
        {
          "name": "new_status",
          "type": "string",
          "required": false
        },
        {
          "name": "event_note",
          "type": "text",
          "required": false,
          "sensitive": true
        },
        {
          "name": "event_file",
          "type": "file",
          "required": false,
          "private": true,
          "sensitive": true
        },
        {
          "name": "actor_id",
          "type": "many-to-one:directus_users",
          "required": false,
          "sensitive": true
        },
        {
          "name": "event_at",
          "type": "datetime",
          "required": true
        },
        {
          "name": "created_at",
          "type": "datetime",
          "required": true,
          "system": true
        }
      ]
    }
  ],
  "directus_permission_note": "School coordinator may view/update only own courier batch actions assigned to school; operations staff manages all courier batches."
}