{
  "module_id": "support_tickets",
  "data_classes": [
    {
      "class": "school_visible",
      "fields": [
        "own ticket subject",
        "own school-visible replies",
        "own attachments",
        "status"
      ],
      "allowed_public_access": false,
      "school_scope_required": true
    },
    {
      "class": "internal",
      "fields": [
        "ticket status",
        "category",
        "priority",
        "assigned queue",
        "SLA status"
      ],
      "allowed_public_access": false
    },
    {
      "class": "sensitive",
      "fields": [
        "description",
        "message body",
        "school_id",
        "student context",
        "payment context",
        "attachment file",
        "resolution summary"
      ],
      "allowed_public_access": false,
      "requires_role_restriction": true
    },
    {
      "class": "restricted",
      "fields": [
        "internal notes",
        "security/privacy ticket details",
        "linked entity raw context",
        "redaction metadata",
        "export payload"
      ],
      "allowed_public_access": false,
      "requires_audit_for_access_or_change": true
    },
    {
      "class": "never_show_in_support_default",
      "fields": [
        "answer keys",
        "raw OMR scans",
        "full payment provider payload",
        "certificate private file URL",
        "provider secrets"
      ],
      "allowed_public_access": false
    },
    {
      "class": "never_browser_trusted",
      "fields": [
        "school_id",
        "ticket_status",
        "priority",
        "assignment",
        "linked_entity_access",
        "message_visibility"
      ],
      "allowed_public_access": false
    }
  ],
  "_meta": {
    "project": "Versa Olympiads",
    "portal": "company_portal",
    "module_id": "support_tickets",
    "generated_at": "2026-06-22T00:00:00+04:00",
    "source": {
      "answered_questionnaire_csv": "source/versa_company_portal_questionnaire_answered_source_of_truth.csv",
      "module_registry_csv": "source/versa_company_portal_module_registry.csv",
      "module_source_trace_csv": "source/support_tickets_module_source_trace.csv",
      "source_trace_row_count": 71
    },
    "generator_note": "Semantic compiled module spec; not a CSV-row wrapper."
  }
}